fxq/geoffrey/__init__.py
fxq/geoffrey/cli.py
fxq/geoffrey/config.py
fxq/geoffrey/exception.py
fxq/geoffrey/geoffreycli.py
fxq/geoffrey/model.py
fxq/geoffrey/repository.py
fxq/geoffrey/runner.py
fxq_geoffrey-1.0.8.dist-info/LICENSE.md
fxq_geoffrey-1.0.8.dist-info/METADATA
fxq_geoffrey-1.0.8.dist-info/WHEEL
fxq_geoffrey-1.0.8.dist-info/entry_points.txt
fxq_geoffrey-1.0.8.dist-info/top_level.txt
fxq_geoffrey-1.0.8.dist-info/RECORD
