Metadata-Version: 2.1
Name: fxq-geoffrey
Version: 1.0.8
Summary: The Provisioning Assistant for Devops, configure snippets as YML and call them from the geoffrey CLI
Home-page: https://bitbucket.org/fxquants/geoffrey
Author: Jonathan Turnock
Author-email: Jonathan.Turnock@fxquants.net
License: MIT
Platform: UNKNOWN
Requires-Dist: Click
Requires-Dist: fxq-commons
Requires-Dist: pyfiglet
Requires-Dist: PyInquirer
Requires-Dist: PyYAML
Requires-Dist: appdirs
